sphinx_swagger-0.0.4.dist-info/DESCRIPTION.rst
sphinx_swagger-0.0.4.dist-info/METADATA
sphinx_swagger-0.0.4.dist-info/RECORD
sphinx_swagger-0.0.4.dist-info/WHEEL
sphinx_swagger-0.0.4.dist-info/entry_points.txt
sphinx_swagger-0.0.4.dist-info/metadata.json
sphinx_swagger-0.0.4.dist-info/top_level.txt
sphinxswagger/__init__.py
sphinxswagger/builder.py
sphinxswagger/command.py
sphinxswagger/document.py
sphinxswagger/writer.py
