Metadata-Version: 2.0
Name: sphinx-swagger
Version: 0.0.4
Summary: Generate swagger definitions from sphinx docs
Home-page: https://github.com/dave-shawley/sphinx-swagger
Author: Dave Shawley
Author-email: daveshawley+python@gmail.com
License: UNKNOWN
Platform: UNKNOWN
Classifier: Intended Audience :: Developers
Classifier: License :: OSI Approved :: BSD License
Classifier: Operating System :: OS Independent
Classifier: Programming Language :: Python
Classifier: Programming Language :: Python :: 2
Classifier: Programming Language :: Python :: 2.7
Classifier: Programming Language :: Python :: 3
Classifier: Programming Language :: Python :: 3.4
Classifier: Framework :: Sphinx :: Extension
Requires-Dist: Sphinx (>=1.4,<2)
Requires-Dist: sphinxcontrib-httpdomain (>=1.5.0)
